npcsh/__init__.py
npcsh/_state.py
npcsh/alicanto.py
npcsh/build.py
npcsh/completion.py
npcsh/config.py
npcsh/conversation_viewer.py
npcsh/corca.py
npcsh/diff_viewer.py
npcsh/execution.py
npcsh/guac.py
npcsh/mcp_helpers.py
npcsh/mcp_server.py
npcsh/npc.py
npcsh/npcsh.py
npcsh/parsing.py
npcsh/plonk.py
npcsh/pti.py
npcsh/routes.py
npcsh/salmon_simulation.py
npcsh/spool.py
npcsh/ui.py
npcsh/wander.py
npcsh/yap.py
npcsh/benchmark/__init__.py
npcsh/benchmark/npcsh_agent.py
npcsh/benchmark/runner.py
npcsh/benchmark/templates/install-npcsh.sh.j2
npcsh/npc_team/alicanto.npc
npcsh/npc_team/alicanto.png
npcsh/npc_team/corca.npc
npcsh/npc_team/corca.png
npcsh/npc_team/corca_example.png
npcsh/npc_team/frederic.npc
npcsh/npc_team/frederic4.png
npcsh/npc_team/guac.npc
npcsh/npc_team/guac.png
npcsh/npc_team/kadiefa.npc
npcsh/npc_team/kadiefa.png
npcsh/npc_team/npcsh.ctx
npcsh/npc_team/npcsh_sibiji.png
npcsh/npc_team/plonk.npc
npcsh/npc_team/plonk.png
npcsh/npc_team/plonkjr.png
npcsh/npc_team/sibiji.npc
npcsh/npc_team/sibiji.png
npcsh/npc_team/spool.png
npcsh/npc_team/yap.png
npcsh/npc_team/jinxs/incognide/add_tab.jinx
npcsh/npc_team/jinxs/incognide/close_pane.jinx
npcsh/npc_team/jinxs/incognide/close_tab.jinx
npcsh/npc_team/jinxs/incognide/confirm.jinx
npcsh/npc_team/jinxs/incognide/focus_pane.jinx
npcsh/npc_team/jinxs/incognide/incognide.jinx
npcsh/npc_team/jinxs/incognide/list_panes.jinx
npcsh/npc_team/jinxs/incognide/navigate.jinx
npcsh/npc_team/jinxs/incognide/notify.jinx
npcsh/npc_team/jinxs/incognide/open_pane.jinx
npcsh/npc_team/jinxs/incognide/read_pane.jinx
npcsh/npc_team/jinxs/incognide/run_terminal.jinx
npcsh/npc_team/jinxs/incognide/send_message.jinx
npcsh/npc_team/jinxs/incognide/split_pane.jinx
npcsh/npc_team/jinxs/incognide/switch_npc.jinx
npcsh/npc_team/jinxs/incognide/switch_tab.jinx
npcsh/npc_team/jinxs/incognide/write_file.jinx
npcsh/npc_team/jinxs/incognide/zen_mode.jinx
npcsh/npc_team/jinxs/lib/browser/browser_action.jinx
npcsh-1.1.22.dist-info/licenses/LICENSE
npcsh-1.1.22.dist-info/METADATA
npcsh-1.1.22.dist-info/WHEEL
npcsh-1.1.22.dist-info/entry_points.txt
npcsh-1.1.22.dist-info/top_level.txt
npcsh-1.1.22.dist-info/RECORD
