Metadata-Version: 2.4
Name: npcsh
Version: 1.1.22
Summary: npcsh is a command-line toolkit for using AI agents in novel ways.
Home-page: https://github.com/NPC-Worldwide/npcsh
Author: Christopher Agostino
Author-email: info@npcworldwi.de
Classifier: Programming Language :: Python :: 3
Classifier: License :: OSI Approved :: MIT License
Requires-Python: >=3.10
License-File: LICENSE
Requires-Dist: npcpy
Requires-Dist: jinja2
Requires-Dist: litellm
Requires-Dist: docx
Requires-Dist: scipy
Requires-Dist: numpy
Requires-Dist: thefuzz
Requires-Dist: imagehash
Requires-Dist: requests
Requires-Dist: chroptiks
Requires-Dist: matplotlib
Requires-Dist: markdown
Requires-Dist: networkx
Requires-Dist: PyYAML
Requires-Dist: PyMuPDF
Requires-Dist: pyautogui
Requires-Dist: pydantic
Requires-Dist: pygments
Requires-Dist: sqlalchemy
Requires-Dist: termcolor
Requires-Dist: rich
Requires-Dist: colorama
Requires-Dist: Pillow
Requires-Dist: python-dotenv
Requires-Dist: pandas
Requires-Dist: beautifulsoup4
Requires-Dist: duckduckgo-search
Requires-Dist: flask
Requires-Dist: flask_cors
Requires-Dist: redis
Requires-Dist: psycopg2-binary
Requires-Dist: flask_sse
Requires-Dist: wikipedia
Requires-Dist: mcp
Provides-Extra: lite
Requires-Dist: anthropic; extra == "lite"
Requires-Dist: openai; extra == "lite"
Requires-Dist: ollama; extra == "lite"
Requires-Dist: google-generativeai; extra == "lite"
Requires-Dist: google-genai; extra == "lite"
Provides-Extra: local
Requires-Dist: sentence_transformers; extra == "local"
Requires-Dist: opencv-python; extra == "local"
Requires-Dist: ollama; extra == "local"
Requires-Dist: kuzu; extra == "local"
Requires-Dist: chromadb; extra == "local"
Requires-Dist: diffusers; extra == "local"
Requires-Dist: nltk; extra == "local"
Requires-Dist: torch; extra == "local"
Requires-Dist: darts; extra == "local"
Provides-Extra: yap
Requires-Dist: pyaudio; extra == "yap"
Requires-Dist: gtts; extra == "yap"
Requires-Dist: playsound==1.2.2; extra == "yap"
Requires-Dist: pygame; extra == "yap"
Requires-Dist: faster_whisper; extra == "yap"
Requires-Dist: pyttsx3; extra == "yap"
Provides-Extra: bench
Requires-Dist: harbor; extra == "bench"
Requires-Dist: terminal-bench; extra == "bench"
Provides-Extra: all
Requires-Dist: anthropic; extra == "all"
Requires-Dist: openai; extra == "all"
Requires-Dist: ollama; extra == "all"
Requires-Dist: google-generativeai; extra == "all"
Requires-Dist: google-genai; extra == "all"
Requires-Dist: sentence_transformers; extra == "all"
Requires-Dist: opencv-python; extra == "all"
Requires-Dist: ollama; extra == "all"
Requires-Dist: kuzu; extra == "all"
Requires-Dist: chromadb; extra == "all"
Requires-Dist: diffusers; extra == "all"
Requires-Dist: nltk; extra == "all"
Requires-Dist: torch; extra == "all"
Requires-Dist: darts; extra == "all"
Requires-Dist: pyaudio; extra == "all"
Requires-Dist: gtts; extra == "all"
Requires-Dist: playsound==1.2.2; extra == "all"
Requires-Dist: pygame; extra == "all"
Requires-Dist: faster_whisper; extra == "all"
Requires-Dist: pyttsx3; extra == "all"
Dynamic: author
Dynamic: author-email
Dynamic: classifier
Dynamic: description
Dynamic: description-content-type
Dynamic: home-page
Dynamic: license-file
Dynamic: provides-extra
Dynamic: requires-dist
Dynamic: requires-python
Dynamic: summary
